dynamic_random_sampler/__init__.pyi
dynamic_random_sampler/dynamic_random_sampler.cpython-312-aarch64-linux-gnu.so
dynamic_random_sampler/py.typed
dynamic_random_sampler/__init__.py
dynamic_random_sampler-26.1.22.0.dist-info/WHEEL
dynamic_random_sampler-26.1.22.0.dist-info/METADATA
dynamic_random_sampler-26.1.22.0.dist-info/RECORD
