Metadata-Version: 2.4
Name: dynamic-random-sampler
Version: 26.1.22.0
Requires-Dist: mkdocs>=1.5 ; extra == 'docs'
Requires-Dist: mkdocs-material>=9.0 ; extra == 'docs'
Requires-Dist: mkdocstrings[python]>=0.24 ; extra == 'docs'
Provides-Extra: docs
Summary: Dynamic weighted random sampling with O(log* N) operations
Requires-Python: >=3.12
